README.txt
bootstrap.py
buildout.cfg
setup.py
collective/__init__.py
collective.trajectory.egg-info/PKG-INFO
collective.trajectory.egg-info/SOURCES.txt
collective.trajectory.egg-info/dependency_links.txt
collective.trajectory.egg-info/entry_points.txt
collective.trajectory.egg-info/namespace_packages.txt
collective.trajectory.egg-info/not-zip-safe
collective.trajectory.egg-info/requires.txt
collective.trajectory.egg-info/top_level.txt
collective/trajectory/__init__.py
collective/trajectory/browser.py
collective/trajectory/components.py
collective/trajectory/configure.zcml
collective/trajectory/utils.py
docs/HISTORY.txt