Metadata-Version: 1.0
Name: collective.trajectory
Version: 0.1
Summary: Traject integration in Plone
Home-page: http://svn.plone.org/svn/collective/collective.trajectory
Author: Izhar Firdaus
Author-email: izhar@inigo-tech.com
License: GPL
Keywords: traject plone routing
Platform: UNKNOWN
Classifier: Programming Language :: Python
